MANIFEST.in
README.rst
setup.py
songvid/__init__.py
songvid/__main__.py
songvid/songvid.py
songvid.egg-info/PKG-INFO
songvid.egg-info/SOURCES.txt
songvid.egg-info/dependency_links.txt
songvid.egg-info/entry_points.txt
songvid.egg-info/top_level.txt